pybats/__init__.py
pybats/_nbdev.py
pybats/analysis.py
pybats/conjugates.py
pybats/dbcm.py
pybats/dcmm.py
pybats/define_models.py
pybats/dglm.py
pybats/dlmm.py
pybats/forecast.py
pybats/latent_factor.py
pybats/latent_factor_fxns.py
pybats/loss_functions.py
pybats/plot.py
pybats/point_forecast.py
pybats/seasonal.py
pybats/shared.py
pybats/update.py
pybats/pkg_data/.DS_Store
pybats/pkg_data/bps_agent_dof.csv
pybats/pkg_data/bps_agent_mean.csv
pybats/pkg_data/bps_agent_var.csv
pybats/pkg_data/bps_inflation.csv
pybats/pkg_data/dbcm_latent_factor_data
pybats/pkg_data/dcmm_latent_factor_data
pybats/pkg_data/dlmm_example_data.csv
pybats/pkg_data/interp_beta.pickle.gzip
pybats/pkg_data/interp_beta_old.pickle.gzip
pybats/pkg_data/interp_gamma.pickle.gzip
pybats/pkg_data/interp_gamma_old.pickle.gzip
pybats/pkg_data/sales.csv
pybats/pkg_data/sim_sales_data
pybats/pkg_data/us_inflation.csv
pybats-0.0.5.dist-info/LICENSE
pybats-0.0.5.dist-info/METADATA
pybats-0.0.5.dist-info/WHEEL
pybats-0.0.5.dist-info/entry_points.txt
pybats-0.0.5.dist-info/top_level.txt
pybats-0.0.5.dist-info/RECORD
