Metadata-Version: 2.1
Name: pybats
Version: 0.0.5
Summary: Pybats is a python library for Bayesian time series analysis.
Home-page: https://github.com/lavinei/pybats/tree/master/
Author: Isaac Lavine
Author-email: lavine.isaac@gmail.com
License: Apache Software License 2.0
Keywords: Time series; Statistics; Dynamic generalized linear models; Forecasting;
Platform: UNKNOWN
Classifier: Development Status :: 4 - Beta
Classifier: Intended Audience :: Developers
Classifier: License :: OSI Approved :: Apache Software License
Classifier: Natural Language :: English
Classifier: Programming Language :: Python :: 3.6
Classifier: Programming Language :: Python :: 3.7
Classifier: Programming Language :: Python :: 3.8
Requires-Python: >=3.6
Requires-Dist: pandas
Requires-Dist: numpy
Requires-Dist: statsmodels
Requires-Dist: scipy
Requires-Dist: matplotlib
Requires-Dist: seaborn
Requires-Dist: nbdev
